dipense/__init__.py
dipense/cli_txt.py
dipense/default.py
dipense/drone.py
dipense/icheckp.py
dipense/structure.py
dipense/tcolor.py
dipense-0.1.5.dist-info/LICENSE
dipense-0.1.5.dist-info/METADATA
dipense-0.1.5.dist-info/WHEEL
dipense-0.1.5.dist-info/top_level.txt
dipense-0.1.5.dist-info/RECORD
