Metadata-Version: 2.1
Name: dipense
Version: 0.1.5
Summary: An OSINT tool for it ninjas.
Home-page: https://dipense.readthedocs.io
Download-URL: https://pypi.org/project/dipense
Author: Usman Musa
Author-email: usmanmusa1920@gmail.com
License: MIT
Project-URL: Documentation, https://dipense.readthedocs.io
Project-URL: Source, https://github.com/usmanmusa1920/dipense
Keywords: dipense
Platform: any
Classifier: Development Status :: 5 - Production/Stable
Classifier: Environment :: Web Environment
Classifier: Intended Audience :: Developers
Classifier: License :: OSI Approved :: MIT License
Classifier: Natural Language :: English
Classifier: Operating System :: MacOS
Classifier: Operating System :: POSIX
Classifier: Programming Language :: Python
Classifier: Programming Language :: Python :: 3
Classifier: Programming Language :: Python :: 3.7
Classifier: Programming Language :: Python :: 3.8
Classifier: Programming Language :: Python :: 3.9
Classifier: Programming Language :: Python :: 3.10
Classifier: Framework :: Django
Classifier: Topic :: Internet
Classifier: Topic :: Terminals
Classifier: Topic :: Security
Classifier: Topic :: Communications :: Email
Classifier: Topic :: Software Development :: Libraries :: Python Modules
Requires-Python: >=3.7
License-File: LICENSE
Requires-Dist: folium (>=0.13.0)
Requires-Dist: phonenumbers (>=8.13.0)
Requires-Dist: geocoder (>=1.38.1)
Requires-Dist: python-whois (>=0.8.0)
Requires-Dist: termcolor (>=2.1.0)
